lyricfetch/__init__.py
lyricfetch/cli.py
lyricfetch/lyrics.py
lyricfetch/run.py
lyricfetch/scraping.py
lyricfetch/song.py
lyricfetch/stats.py
lyricfetch-2.1.0.dist-info/LICENSE
lyricfetch-2.1.0.dist-info/METADATA
lyricfetch-2.1.0.dist-info/WHEEL
lyricfetch-2.1.0.dist-info/entry_points.txt
lyricfetch-2.1.0.dist-info/top_level.txt
lyricfetch-2.1.0.dist-info/RECORD
